pygifdec.cpython-310-darwin.so
src/gifdec.h
pygifdec-0.0.2.dist-info/LICENSE
pygifdec-0.0.2.dist-info/METADATA
pygifdec-0.0.2.dist-info/WHEEL
pygifdec-0.0.2.dist-info/top_level.txt
pygifdec-0.0.2.dist-info/RECORD
