Metadata-Version: 2.1
Name: pygifdec
Version: 0.0.2
Summary: a python gifdec wrapper
Home-page: https://github.com/alingse/pygifdec
Author: alingse
Author-email: alingse@foxmail.com
License-File: LICENSE
